{
	"client": "./client",
	"svr": "./server",
	"miniprogramRoot": "./client",
	"qcloudRoot": "./server",
	"setting": {
		"urlCheck": false,
		"es6": true,
		"postcss": true,
		"minified": true,
		"newFeature": true
	},
	"appid": "wx13ec741be3001633",
	"projectname": "%E5%BE%AE%E6%B8%B8",
	"compileType": "miniprogram",
	"condition": {
		"search": {
			"current": -1,
			"list": []
		},
		"conversation": {
			"current": -1,
			"list": []
		},
		"plugin": {
			"current": -1,
			"list": []
		},
		"game": {
			"list": []
		},
		"miniprogram": {
			"current": -1,
			"list": []
		}
	}
}